knet.py
kvadratnet.py
kvadratnet-0.3.0.dist-info/DESCRIPTION.rst
kvadratnet-0.3.0.dist-info/METADATA
kvadratnet-0.3.0.dist-info/RECORD
kvadratnet-0.3.0.dist-info/WHEEL
kvadratnet-0.3.0.dist-info/entry_points.txt
kvadratnet-0.3.0.dist-info/metadata.json
kvadratnet-0.3.0.dist-info/top_level.txt
