Metadata-Version: 2.0
Name: kvadratnet
Version: 0.3.0
Summary: Python tools for working with the Danish Kvadratnet tiling scheme.
Home-page: https://github.com/kbevers/kvadratnet
Author: Kristian Evers
Author-email: kristianevers@gmail.com
License: ISC
Keywords: kvadratnet gis tiling
Platform: UNKNOWN
Classifier: Development Status :: 3 - Alpha
Classifier: Intended Audience :: Developers
Classifier: Intended Audience :: Science/Research
Classifier: License :: OSI Approved :: ISC License (ISCL)
Classifier: Topic :: Scientific/Engineering :: GIS
Classifier: Topic :: Utilities
